[{"class_name": "pottedplant", "bbox": ["510", "2", "633", "179"], "used": false}, {"class_name": "pictureframe", "bbox": ["556", "145", "636", "205"], "used": false}, {"class_name": "sofa", "bbox": ["11", "151", "210", "476"], "used": false}, {"class_name": "coffeetable", "bbox": ["495", "283", "639", "475"], "used": false}, {"class_name": "pillow", "bbox": ["3", "145", "90", "301"], "used": false}, {"class_name": "coffeetable", "bbox": ["518", "177", "636", "271"], "used": false}, {"class_name": "chair", "bbox": ["3", "79", "90", "183"], "used": true}]